autowk/AutoWKBase.py
autowk/AutoWKListen.py
autowk/AutoWKOptions.py
autowk/AutoWkDriverClient.py
autowk/Element.py
autowk/__init__.py
autowk/__pycache__/AutoWKBase.cpython-310.pyc
autowk/__pycache__/AutoWKListen.cpython-310.pyc
autowk/__pycache__/AutoWKOptions.cpython-310.pyc
autowk/__pycache__/AutoWkDriverClient.cpython-310.pyc
autowk/__pycache__/Element.cpython-310.pyc
autowk/__pycache__/__init__.cpython-310.pyc
autowk/bin/ImageDiff.exe
autowk/bin/ImageDiff.exe.manifest
autowk/bin/JavaScriptCore.dll
autowk/bin/JavaScriptCore.dll.manifest
autowk/bin/LLIntOffsetsExtractor.exe
autowk/bin/LLIntOffsetsExtractor.exe.manifest
autowk/bin/LLIntSettingsExtractor.exe
autowk/bin/LLIntSettingsExtractor.exe.manifest
autowk/bin/MiniBrowser.exe
autowk/bin/MiniBrowserInjectedBundle.dll
autowk/bin/MiniBrowserInjectedBundle.dll.manifest
autowk/bin/WebCore.dll
autowk/bin/WebCore.dll.manifest
autowk/bin/WebDriver.exe
autowk/bin/WebDriver.exe.manifest
autowk/bin/WebKit2.dll
autowk/bin/WebKit2.dll.manifest
autowk/bin/WebKitGPUProcess.exe
autowk/bin/WebKitNetworkProcess.exe
autowk/bin/WebKitTestRunner.exe
autowk/bin/WebKitTestRunnerWS.exe
autowk/bin/WebKitTestRunnerWS.exe.manifest
autowk/bin/WebKitWebProcess.exe
autowk/bin/brotlicommon.dll
autowk/bin/brotlidec.dll
autowk/bin/brotlienc.dll
autowk/bin/closePage.html
autowk/bin/crypto-56.dll
autowk/bin/harfbuzz-icu.dll
autowk/bin/harfbuzz.dll
autowk/bin/icudt77.dll
autowk/bin/icuin77.dll
autowk/bin/icuuc77.dll
autowk/bin/jpeg62.dll
autowk/bin/jsc.exe
autowk/bin/jsc.exe.manifest
autowk/bin/jxl.dll
autowk/bin/jxl_cms.dll
autowk/bin/lcms2-2.dll
autowk/bin/libEGL.dll
autowk/bin/libEGL.dll.manifest
autowk/bin/libGLESv2.dll
autowk/bin/libGLESv2.dll.manifest
autowk/bin/libcurl.dll
autowk/bin/libpng16.dll
autowk/bin/libsharpyuv.dll
autowk/bin/libwebp.dll
autowk/bin/libwebpdemux.dll
autowk/bin/libwebpmux.dll
autowk/bin/libxml2.dll
autowk/bin/libxslt.dll
autowk/bin/nghttp2.dll
autowk/bin/nghttp3.dll
autowk/bin/ngtcp2.dll
autowk-0.4.2.dist-info/METADATA
autowk-0.4.2.dist-info/WHEEL
autowk-0.4.2.dist-info/top_level.txt
autowk-0.4.2.dist-info/RECORD
