Metadata-Version: 2.1
Name: autowk
Version: 0.4.2
Summary: 基于WebKit的自动化浏览器框架
Home-page: https://github.com/LoseNine/AutoWK
Author: ruyi
Author-email: losenine@163.com
Classifier: Programming Language :: Python :: 3
Classifier: License :: OSI Approved :: BSD License
Classifier: Operating System :: Microsoft :: Windows
Requires-Python: >=3.7
Requires-Dist: psutil>=5.9.0
